azure_devops_repository_archiver/__init__.py
azure_devops_repository_archiver/py.typed
azure_devops_repository_archiver/_jsii/__init__.py
azure_devops_repository_archiver/_jsii/azure-devops-repository-archiver@1.6.24.jsii.tgz
azure_devops_repository_archiver-1.6.24.dist-info/LICENSE
azure_devops_repository_archiver-1.6.24.dist-info/METADATA
azure_devops_repository_archiver-1.6.24.dist-info/WHEEL
azure_devops_repository_archiver-1.6.24.dist-info/top_level.txt
azure_devops_repository_archiver-1.6.24.dist-info/RECORD
