Metadata-Version: 2.1
Name: azure-devops-repository-archiver
Version: 1.6.24
Summary: Archive Azure DevOps git repositories to AWS S3
Home-page: https://github.com/stefanfreitag/azure_s3_repository_archiver.git
Author: Stefan Freitag<stefan.freitag@udo.edu>
License: Apache-2.0
Project-URL: Source, https://github.com/stefanfreitag/azure_s3_repository_archiver.git
Classifier: Intended Audience :: Developers
Classifier: Operating System :: OS Independent
Classifier: Programming Language :: JavaScript
Classifier: Programming Language :: Python :: 3 :: Only
Classifier: Programming Language :: Python :: 3.9
Classifier: Programming Language :: Python :: 3.10
Classifier: Programming Language :: Python :: 3.11
Classifier: Typing :: Typed
Classifier: Development Status :: 5 - Production/Stable
Classifier: License :: OSI Approved
Requires-Python: ~=3.9
License-File: LICENSE
Requires-Dist: aws-cdk-lib<3.0.0,>=2.160.0
Requires-Dist: constructs<11.0.0,>=10.0.5
Requires-Dist: jsii<2.0.0,>=1.112.0
Requires-Dist: publication>=0.0.3
Requires-Dist: typeguard<4.3.0,>=2.13.3
